roughsets_base/__init__.py
roughsets_base/roughset_dt.py
roughsets_base/roughset_si.py
roughsets_base-1.0.1.2.dist-info/LICENSE
roughsets_base-1.0.1.2.dist-info/LICENSE.txt
roughsets_base-1.0.1.2.dist-info/METADATA
roughsets_base-1.0.1.2.dist-info/WHEEL
roughsets_base-1.0.1.2.dist-info/top_level.txt
roughsets_base-1.0.1.2.dist-info/RECORD
