Metadata-Version: 2.1
Name: roughsets-base
Version: 1.0.1.2
Summary: "The library contains base functions of the RoughSets Theory (introduced by Zdzisław Pawlak in 1982)."
Home-page: https://github.com/darekjk/roughsets-base
Author: Dariusz Jankowski
Author-email: darekjki@gmail.com
Project-URL: Bug Tracker, https://github.com/darekjk/roughsets-base/issues
Project-URL: Documentation, https://github.com/darekjk/roughsets-base/
Project-URL: Source Code, https://github.com/darekjk/roughsets-base
Classifier: Development Status :: 5 - Production/Stable
Classifier: Topic :: Scientific/Engineering
Classifier: Topic :: Software Development :: Libraries :: Python Modules
Classifier: Intended Audience :: Science/Research
Classifier: Intended Audience :: Developers
Classifier: License :: OSI Approved :: BSD License
Classifier: Programming Language :: Python :: 3
Classifier: Operating System :: OS Independent
Classifier: Environment :: Console
Classifier: Natural Language :: English
Requires-Python: >=3.8
License-File: LICENSE
License-File: LICENSE.txt
Requires-Dist: pandas (>=1.2)
